wyzard/__init__.py
wyzard/exceptions.py
wyzard/gpt_detector.py
wyzard/image_captioning.py
wyzard/object_detection.py
wyzard/utils.py
wyzard-1.0.dist-info/LICENSE
wyzard-1.0.dist-info/METADATA
wyzard-1.0.dist-info/WHEEL
wyzard-1.0.dist-info/top_level.txt
wyzard-1.0.dist-info/RECORD
