Metadata-Version: 2.1
Name: wyzard
Version: 1.0
Summary: Run various transformers models from one packages.
Home-page: https://github.com/LyQuid12/Wyzard
Author: LyQuid
Author-email: lyquidpersonal@gmail.com
License: MIT License
Project-URL: Source Code, https://github.com/LyQuid12/Wyzard
Project-URL: Discord, https://discord.gg/qpT2AeYZRN
Project-URL: Issue tracker, https://github.com/LyQuid12/Wyzard/issues
Keywords: python,machine learning,ml,ai,artificial intelligence,transformers,pytorch,models,tokenizer
Classifier: Development Status :: 4 - Beta
Classifier: Intended Audience :: Developers
Classifier: Intended Audience :: Science/Research
Classifier: Topic :: Scientific/Engineering :: Artificial Intelligence
Classifier: Programming Language :: Python :: 3.7
Classifier: Programming Language :: Python :: 3.8
Classifier: Programming Language :: Python :: 3.9
Classifier: Programming Language :: Python :: 3.10
Classifier: License :: OSI Approved :: MIT License
Classifier: Operating System :: Microsoft :: Windows
Classifier: Operating System :: MacOS
Classifier: Operating System :: POSIX :: Linux
License-File: LICENSE
Requires-Dist: transformers
Requires-Dist: diffusers
Requires-Dist: Pillow
Requires-Dist: torch
Requires-Dist: matplotlib
Requires-Dist: Cython
